pyls_black/__init__.py
pyls_black/plugin.py
pyls_black-0.4.7.dist-info/LICENSE
pyls_black-0.4.7.dist-info/METADATA
pyls_black-0.4.7.dist-info/WHEEL
pyls_black-0.4.7.dist-info/entry_points.txt
pyls_black-0.4.7.dist-info/top_level.txt
pyls_black-0.4.7.dist-info/RECORD
