Metadata-Version: 2.1
Name: pyls-black
Version: 0.4.7
Summary: Black plugin for the Python Language Server
Home-page: https://github.com/rupert/pyls-black
Author: Rupert Bedford
Author-email: rupert@rupertb.com
License: UNKNOWN
Platform: UNKNOWN
Classifier: Programming Language :: Python
Classifier: License :: OSI Approved :: MIT License
Classifier: Operating System :: OS Independent
Requires-Python: >=3.6
Provides-Extra: dev
